adafruit_ble_apple_notification_center.py
adafruit_circuitpython_ble_apple_notification_center-0.10.14.dist-info/licenses/LICENSE
adafruit_circuitpython_ble_apple_notification_center-0.10.14.dist-info/METADATA
adafruit_circuitpython_ble_apple_notification_center-0.10.14.dist-info/WHEEL
adafruit_circuitpython_ble_apple_notification_center-0.10.14.dist-info/top_level.txt
adafruit_circuitpython_ble_apple_notification_center-0.10.14.dist-info/RECORD
