Metadata-Version: 2.4
Name: adafruit-circuitpython-ble-apple-notification-center
Version: 0.10.14
Summary: BLE library for the Apple Notification Center
Author-email: Adafruit Industries <circuitpython@adafruit.com>
License: MIT
Project-URL: Homepage, https://github.com/adafruit/Adafruit_CircuitPython_BLE_Apple_Notification_Center
Keywords: adafruit,blinka,circuitpython,micropython,ble_apple_notification_center,ble,ancs,apple,notification
Classifier: Intended Audience :: Developers
Classifier: Topic :: Software Development :: Libraries
Classifier: Topic :: Software Development :: Embedded Systems
Classifier: Topic :: System :: Hardware
Classifier: License :: OSI Approved :: MIT License
Classifier: Programming Language :: Python :: 3
License-File: LICENSE
Requires-Dist: Adafruit-Blinka
Requires-Dist: adafruit-circuitpython-ble
Provides-Extra: optional
Dynamic: license-file
